ipdw/__init__.py
ipdw/interpolate.py
ipdw-1.0.1.dist-info/LICENSE
ipdw-1.0.1.dist-info/METADATA
ipdw-1.0.1.dist-info/WHEEL
ipdw-1.0.1.dist-info/top_level.txt
ipdw-1.0.1.dist-info/RECORD
