Metadata-Version: 2.1
Name: ipdw
Version: 1.0.1
Summary: Inverse-Path-Distance-Weighted Interpolation for Python
Home-page: https://github.com/wrightky/ipdw
Author: Kyle Wright
Author-email: Kyle.Wright@twdb.texas.gov
License: MIT
Keywords: interpolation ipdw idw
Classifier: Programming Language :: Python
Classifier: Programming Language :: Python :: 3.9
Classifier: Programming Language :: Python :: 3.10
Classifier: Programming Language :: Python :: 3.11
Classifier: Natural Language :: English
Classifier: Operating System :: OS Independent
Classifier: Topic :: Scientific/Engineering :: GIS
License-File: LICENSE
Requires-Dist: numpy
Requires-Dist: matplotlib
Requires-Dist: scikit-fmm
